{"event": "page_view", "lesson_id": "50.0", "timestamp": "2025-04-21 02:25:32.709293"}
{"event": "page_view", "lesson_id": "50.0", "timestamp": "2025-04-21 02:47:33.634769"}
{"event": "page_view", "lesson_id": "1", "timestamp": "2025-04-21 02:53:56.711106"}
{"event": "page_view", "lesson_id": "2", "timestamp": "2025-04-21 02:54:09.244113"}
{"event": "page_view", "lesson_id": "1", "timestamp": "2025-04-21 02:54:59.379469"}
{"event": "page_view", "lesson_id": "1", "timestamp": "2025-04-21 02:59:30.629253"}
{"event": "page_view", "lesson_id": "2", "timestamp": "2025-04-21 03:00:01.198267"}
{"event": "page_view", "lesson_id": "1", "timestamp": "2025-04-21 03:00:17.144242"}
{"event": "page_view", "lesson_id": "1", "timestamp": "2025-04-21 03:02:35.966689"}
{"event": "page_view", "lesson_id": "2", "timestamp": "2025-04-21 03:02:48.147245"}
{"event": "page_view", "lesson_id": "1", "timestamp": "2025-04-21 03:03:51.540980"}
{"event": "page_view", "lesson_id": "2", "timestamp": "2025-04-21 03:03:54.218659"}
{"event": "page_view", "lesson_id": "1", "timestamp": "2025-04-21 03:06:14.635753"}
{"event": "page_view", "lesson_id": "2", "timestamp": "2025-04-21 03:06:18.415739"}
{"event": "page_view", "lesson_id": "3", "timestamp": "2025-04-21 03:06:26.659422"}
{"event": "page_view", "lesson_id": "1", "timestamp": "2025-04-21 03:14:15.817668"}
{"event": "page_view", "lesson_id": "2", "timestamp": "2025-04-21 03:14:23.254804"}
{"event": "page_view", "lesson_id": "3", "timestamp": "2025-04-21 03:14:43.595558"}
{"event": "page_view", "lesson_id": "4", "timestamp": "2025-04-21 03:15:13.008555"}
{"event": "page_view", "lesson_id": "5", "timestamp": "2025-04-21 03:15:39.986570"}
{"event": "page_view", "lesson_id": "4", "timestamp": "2025-04-21 03:18:38.692214"}
{"event": "page_view", "lesson_id": "5", "timestamp": "2025-04-21 03:18:54.995878"}
{"event": "page_view", "lesson_id": "6", "timestamp": "2025-04-21 03:19:34.309603"}
